cli_executor/__init__.py
cli_executor/server.py
cli_executor_mcp-1.0.4.dist-info/licenses/LICENSE
cli_executor_mcp-1.0.4.dist-info/METADATA
cli_executor_mcp-1.0.4.dist-info/WHEEL
cli_executor_mcp-1.0.4.dist-info/entry_points.txt
cli_executor_mcp-1.0.4.dist-info/top_level.txt
cli_executor_mcp-1.0.4.dist-info/RECORD
