Metadata-Version: 2.4
Name: cli-executor-mcp
Version: 1.0.4
Summary: 基于FastMCP的MCP服务器，用于执行CLI命令
Author-email: CaptainJi <jiqing19861123@163.com>
License-Expression: MIT
Project-URL: Homepage, https://github.com/CaptainJi/cli_executor
Project-URL: Bug Tracker, https://github.com/CaptainJi/cli_executor/issues
Classifier: Programming Language :: Python :: 3
Classifier: Programming Language :: Python :: 3.8
Classifier: Programming Language :: Python :: 3.9
Classifier: Programming Language :: Python :: 3.10
Classifier: Programming Language :: Python :: 3.11
Classifier: Programming Language :: Python :: 3.12
Classifier: Operating System :: OS Independent
Classifier: Development Status :: 5 - Production/Stable
Classifier: Intended Audience :: Developers
Classifier: Topic :: Software Development :: Libraries :: Python Modules
Requires-Python: >=3.8
License-File: LICENSE
Requires-Dist: fastmcp>=2.11.0
Requires-Dist: httpx>=0.24.0
Requires-Dist: loguru
Provides-Extra: dev
Requires-Dist: loguru>=0.7.0; extra == "dev"
Requires-Dist: pytest>=7.0.0; extra == "dev"
Requires-Dist: pytest-asyncio>=0.21.0; extra == "dev"
Dynamic: license-file
